{
  "_id": "682dc44c04486e909646cd33",
  "title": "Poison",
  "artist": "Alice Cooper",
  "lyrics": "[intro-single strums]\n(Dm) Your cruel… (Bb) device… (F) your blood… (C) like ice\n(Gm) One look… (Eb) could kill… (Bb) my pain (D - strum) your thrill (D)\n \n(Gm) I wanna (Eb)love you, but I (Bb)better not (F)touch don't (Cm)touch\nI wanna (Ab)hold you, but my (Eb)sen-ses (Bb)tell me to (Am)stop\nI wanna (F)kiss you, but I (C)want it too (G)much too (Dm)much\nI wanna (Bb)taste you, but your (F)lips are (C)venomous\n(Dm)Poison (Bb) (F) (C)\nYou're (Dm)poison (Bb)runnin (F)through my (C)veins\nYou're (Dm)poison (Bb) (F) (C)\n(Dm)I don't (Bb)wanna (F)break these (C)chains (Bb) (Bb)\n \n[single strums]\n(Dm) Your mouth (Bb) so hot (F) Your web (C) I'm caught\n(Gm) Your skin (Eb) so wet (Bb) Black lace (D - Strumming) on sweat (D)\n \n(Gm) I hear you (Eb)callin and it's (Bb)needles and (F)pins and (Cm)pins\nI wanna (Ab)hurt you just to (Eb)hear you (Bb)screaming my (Am)name\nDon't wanna (F)touch you, but you're (C)under my (G)skin deep (Dm)in\nI wanna (Bb)kiss you, but your (F)lips are (C)venomous\n(Dm)poison (Bb) (F) (C)\nYou're (Dm)poison (Bb)runnin (F)through my (C)veins\nYou're (Dm)poison (Bb) (F) (C)\n(Dm)I don't (Bb)wanna (F)break these (C)chains\n(Bb)Poison (D)\n \n(Gm) One look, one (Eb)look, could kill could (Bb)kill\nMy pain (D) your thrill (D)\n \n(Gm) I wanna (Eb)love you, but I (Bb)better not (F)touch don't (Cm)touch\nI wanna (Ab)hold you, but my (Eb)senses (Bb)tell me to (Am)stop\nI wanna (F)kiss you, but I (C)want it too (G)much too (Dm)much\nI wanna (Bb)taste you, but your (F)lips are (C)venomous\n(Dm)poison (Bb) (F) (C)\nYou're (Dm)poison (Bb)runnin (F)through my (C)veins\nYou're (Dm)poison (Bb) (F) (C)\n(Dm)I don't (Bb)wanna (F)break these (C)chains.        (Gm) Poison (Bb)\n \n(Dm) Runnin (Bb)deep in(F)side my (C)veins\n(Dm) Burnin (Bb)deep in(F)side my (C)veins\n(Dm)I don't (Bb)wanna (F)break these (C)chains\n(Dm-single strum) [end]",
  "chords": [
    "Ab",
    "Am",
    "Bb",
    "C",
    "Cm",
    "D",
    "Dm",
    "Eb",
    "F",
    "G",
    "Gm"
  ]
}