{
  "_id": "682dc41904486e909646cbbb",
  "title": "Believe",
  "artist": "Cher",
  "lyrics": "[intro] (F)\n(F) No matter how hard I try, (Am) you keep pushing me aside\nAnd I (Bb)can't break through, there's no (C)talking to you\nSo (F)sad that you're leaving, it takes (Am)time to believe it\n(Bb) But after all is said and done, (C) you're going to be the lonely one, Oh Oh\n \n[chorus]\n(F) Do you be-(C)lieve in life after (Gm)love (Bb)\nI can (F)feel something in-(C)side me say\nI (Gm)really don't think you're (Bb)strong enough now\n(F) Do you be-(C)lieve in life after (Gm)love (Bb)\nI can (F)feel something in-(C)side me say\nI (Gm)really don't think you're (Bb)strong enough now\n \n(F) What am I supposed to do, (Am) sit around and wait for you\nAnd I (Bb)can't do that, there's (C)no turning back\nI need (F)time to move on, I need (Am)love to feel strong\n(Bb) 'Cause I've had time to think it through (C) and maybe I'm too good for you Ohh Oh\n \n[chorus]\n(F) Do you be-(C)lieve in life after (Gm)love (Bb)\nI can (F)feel something in-(C)side me say\nI (Gm)really don't think you're (Bb)strong enough now\n(F) Do you be-(C)lieve in life after (Gm)love (Bb)\nI can (F)feel something in-(C)side me say\nI (Gm)really don't think you're (Bb)strong enough now\n \n(Dm) But I know that I'll get (C)through this\n(Dm) 'Cause I know that I am (C)strong\nI don't (Bb)need you anymore Oh I don't (C)need you anymore\nI don't (Bb)need you anymore, no I don't (C)need you anymore\n \n[chorus]\n(F) Do you be-(C)lieve in life after (Gm)love (Bb)\nI can (F)feel something in-(C)side me say\nI (Gm)really don't think you're (Bb)strong enough now\n(F) Do you be-(C)lieve in life after (Gm)love (Bb)\nI can (F)feel something in-(C)side me say\nI (Gm)really don't think you're (Bb)strong enough now\n(F) [end]",
  "chords": [
    "Am",
    "Bb",
    "C",
    "Dm",
    "F",
    "Gm"
  ]
}