{
  "_id": "682dc45204486e909646cd5d",
  "title": "Shape Of You",
  "artist": "Ed Sheeran",
  "lyrics": "[intro] (Am)  (Dm)  (F)  (G)\n \nThe (Am)club isn't the best place (Dm) to find a lover so the (F)bar is where I go (G)\n(Am)Me and my friends at the (Dm)table doing shots, drinking (F)fast and then we talk slow (G)\nAnd you come (Am)over and start up a conver(Dm)sation with just me\nAnd (F)trust me I'll give it a chance (G) now\nTake my (Am)hand, stop, put Van the (Dm)Man on the jukebox\nAnd (F)then we start to dance, (G) and now I'm singing like\n \n[pre-chorus]\n(Am)Girl, you know I (Dm)want your love\n(F)Your love was handmade (G)for somebody like (Am)me\nCome on now, (Dm)follow my lead\n(F)I may be crazy, (G)don't mind me\nSay, (Am)boy, let's not (Dm)talk too much\n(F)Grab on my waist and (G)put that body on (Am)me\nCome on now, (Dm)follow my lead\nCome, (F)come on now, follow my (G)lead\n \n[chorus]\n(Am) I'm in (Dm)love with the shape of (F)you\nWe push and (G)pull like a magnet (Am)do\nAlthough my (Dm)heart is falling (F)too\nI'm in (G)love with your body\n(Am) And last (Dm)night you were in my (F)room\nAnd now my (G)bed sheets smell like (Am)you\nEvery day discove(Dm)ring something brand (F)new\nI'm in (G)love with your body\n(Am)Oh-I-oh-I-(Dm)oh-I-oh-I (F) I'm in (G)love with your body  x3\n(Am) Every day discove(Dm)ring something brand (F)new\nI'm in (G)love with the shape of you\n \n(Am)One week in we let the (Dm)story begin\nWe're going (F)out on our first date (G)\nYou and (Am)me are thrifty, so go (Dm)all you can eat\nFill up your (F)bag and I fill up a plate (G)\nWe talk for (Am)hours and hours about the (Dm)sweet and the sour\nAnd how your (F)family is doing okay (G)\nLeave and (Am)get in a taxi, then (Dm)kiss in the backseat\nTell the (F)driver make the radio play, (G) and I'm singing like\n \n[pre-chorus]\n(Am)Girl, you know I (Dm)want your love\n(F)Your love was handmade (G)for somebody like (Am)me\nCome on now, (Dm)follow my lead\n(F)I may be crazy, (G)don't mind me\nSay, (Am)boy, let's not (Dm)talk too much\n(F)Grab on my waist and (G)put that body on (Am)me\nCome on now, (Dm)follow my lead\nCome, (F)come on now, follow my (G)lead\n \n[chorus]\n(Am) I'm in (Dm)love with the shape of (F)you\nWe push and (G)pull like a magnet (Am)do\nAlthough my (Dm)heart is falling (F)too\nI'm in (G)love with your body\n(Am) And last (Dm)night you were in my (F)room\nAnd now my (G)bed sheets smell like (Am)you\nEvery day discove(Dm)ring something brand (F)new\nI'm in (G)love with your body\n(Am)Oh-I-oh-I-(Dm)oh-I-oh-I (F) I'm in (G)love with your body  x3\n(Am) Every day discove(Dm)ring something brand (F)new\nI'm in (G)love with the shape of you\n \n(Am) Come on, be my (Dm)baby, come on, (F) come on, be my (G)baby, come on  x4\n \n[chorus]\n(Am) I'm in (Dm)love with the shape of (F)you\nWe push and (G)pull like a magnet (Am)do\nAlthough my (Dm)heart is falling (F)too\nI'm in (G)love with your body\n(Am) And last (Dm)night you were in my (F)room\nAnd now my (G)bed sheets smell like (Am)you\nEvery day discove(Dm)ring something brand (F)new\nI'm in (G)love with your body\n(Am) Come on, be my (Dm)baby, come on, (F) come on, be my (G)baby, come on  x3\n(Am) Every day discove(Dm)ring something brand (F)new\nI'm in (G)love with the shape of (Am-single strum)you [end]",
  "chords": [
    "Am",
    "Dm",
    "F",
    "G"
  ]
}