{
  "_id": "682dc46a04486e909646ce03",
  "title": "Upside Down",
  "artist": "Jack Johnson",
  "lyrics": "[intro] | (C) | (Dm) | x2\n \n(C)Who's to say…  \nWhat's impossible, well (Dm)they forgot\nThis world keeps spinning and with (C)each new day\nI can feel a change in (Dm)everything\nAnd as the surface breaks re(C)flections fade\nBut in some ways they re(Dm)main the same\nAnd as my mind begins to (C)spread its wings\nThere's no stopping curi(Dm)osity (Dm-stop)\n \n[chorus]                                    \nI want to turn the whole thing (C)upside (Dm)down\n(F) I will find the (G)things they say just (C)can't be (Dm) found\n(F) I'll share this (G)love I find with (C)every(Dm)one\n(F) We'll sing and (G)dance to Mother (C)Nature's (Dm) songs\n(F) I don't want this (G)feeling to go away\n[interlude] | (C) | (Dm) | x2\n \n(C)Who's to say…\nI can't do everything, well (Dm)I can try\nAnd as I roll along I be(C)gin to find\nThings aren't always just (Dm)what they seem (Dm-stop)\n \n[chorus]                                    \nI want to turn the whole thing (C)upside (Dm)down\n(F) I will find the (G)things they say just (C)can't be (Dm) found\n(F) I'll share this (G)love I find with (C)every(Dm)one\n(F) We'll sing and (G)dance to Mother (C)Nature's (Dm) songs\n(F) This world keeps (G)spinning and there's (Em)no… time to (Dm)waste\nWell it (Em)all… keeps (Dm)spinning spinning (G)round and round and\n(C)Upside (Dm)down\n(F) Who's to say what's im(G)possible and (C)can't be (Dm) found\n(F) I don't want this (G)feeling to go away\n[outro] | (C) | (Dm) Please don't go away\n| (C) | (Dm) Is this how it's supposed to be\n(C) [end]",
  "chords": [
    "C",
    "Dm",
    "Em",
    "F",
    "G"
  ]
}