{
  "_id": "682dc43404486e909646cc7b",
  "title": "House Of The Rising Sun (abridged)",
  "artist": "The Animals",
  "lyrics": "[If F7 is tricky, play F instead]\n \n[intro]\n(Am) (C) (D) (F)\n(Am) (E7) (Am) (E7)\n \nThere (Am)is a (C)house in (D)New Orleans (F)\nThey (Am)call the (C)Rising (E7)Sun (E7)\nAnd it’s (Am)been the (C)ruin of (D)many a poor boy (F)\nAnd (Am)God I (E7)know I’m\n(Am)one (C) (D) (F)\n(Am) (E7) (Am) (E7)\n \nMy (Am)mother (C)was a (D)tailor (F7)\nShe (Am)sewed my (C)new blue (E7)jeans (E7)\nMy (Am)father (C)was a (D)gambling (F)man\n(Am)Down in (E7)New Or(Am)leans (E7)\n \nOh (Am)mother (C) tell your chil(D)dren (F7)\nNot to (Am)do what (C)I have (E7)done (E7)\n(Am)Spend your (C)lives in (D)sin and mise(F)ry\nIn the (Am)house of the (E7)Rising (Am)Sun (E7)\n \nWell I got (Am)one foot (C) on the (D)platform (F7)\nAnd the (Am)other (C)foot on the (E7)train (E7)\nI’m (Am)going (C)back to (D)New Orleans (F7)\nTo (Am)wear that (E7)ball and\n(Am)chain (C) (D) (F7)\n(Am) (E7) (Am) (E7)\n \nThere (Am)is a (C)house in (D)New Orleans (F7)\nThey (Am)call the (C)Rising (E7)Sun (E7)\nAnd it’s (Am)been the (C)ruin of (D)many a poor (F7)boy\nAnd (Am)God I (E7)know I’m\n(Am)one (C) (D) (F7)\n(Am) (E7) (Am) (Dm)\n(Am) (Dm) - for four bars\n(Am-single strum) [end]",
  "chords": [
    "Am",
    "C",
    "D",
    "Dm",
    "E7",
    "F",
    "F7"
  ]
}