{
  "_id": "682dc43c04486e909646ccaf",
  "title": "I’ll Be There For You (Friends theme tune)",
  "artist": "The Rembrandts",
  "lyrics": "[intro] (G) (G) (G) (F)\n \n(G) So no one told you life was gonna be this (F)way [only clap here!]\n(G) Your job's a joke, you're broke, your love life's D O (Bm)A\n(F) It's like you're (C)always stuck in (G)second gear\nWhen it (F)hasn't been your (C)day, your week\nYour (D)month or even your (D7)year but\n \n[chorus]\n(G) I'll be (C)there for (D)you\n(When the rain starts to (G)pour)\nI'll be (C)there for (D)you\n(Like I've been there be(G)fore)\nI'll be (C)there for (D)you\n('Cause you're there for me (F)too)\n \n(G) You're still in bed at ten and work began at (F)eight\n(G) You've burned your breakfast so far things are going (Bm)great\n(F) Your mother (C)warned you there'd be (G)days like these\nBut she (F)didn't tell you (C)when the world\nHas (D)brought… you down to your (D7)knees that\n \n[chorus]\n(G) I'll be (C)there for (D)you\n(When the rain starts to (G)pour)\nI'll be (C)there for (D)you\n(Like I've been there be(G)fore)\nI'll be (C)there for (D)you\n('Cause you're there for me (F)too)\n \n(C) No one could ever know me… no one could ever see me\n(Em) Since you're the only one who knows… what it's like to be me\n(Am) Someone to face the day with… make it through all the rest with\n(F) Someone I'll always laugh with… (D) even at my (C)worst\nI'm (D)best with (Em)youuuuuuuuuuu, yeah (C) (C)\n \n(F) It's like you're (C)always stuck in (G)second gear\nWhen it (F)hasn't been your (C)day, your week\nYour (D)month or even your (D7)year but\n \n[chorus]\n(G) I'll be (C)there for (D)you\n(When the rain starts to (G)pour)\nI'll be (C)there for (D)you\n(Like I've been there be(G)fore)\nI'll be (C)there for (D)you\n('Cause you're there for me (F)too)\n \n[chorus again!]\n(G) I'll be (C)there for (D)you\n(When the rain starts to (G)pour)\nI'll be (C)there for (D)you\n(Like I've been there be(G)fore)\nI'll be (C)there for (D)you\n('Cause you're there for me (F)too)\n(G-single strum) [end]",
  "chords": [
    "Bm",
    "C",
    "D",
    "D7",
    "Em",
    "F",
    "G"
  ]
}